PyRandomString/__init__.py
pyrandomstring-0.0.6.dist-info/LICENSE
pyrandomstring-0.0.6.dist-info/METADATA
pyrandomstring-0.0.6.dist-info/WHEEL
pyrandomstring-0.0.6.dist-info/top_level.txt
pyrandomstring-0.0.6.dist-info/RECORD
