Metadata-Version: 2.1
Name: pyrandomstring
Version: 0.0.6
Summary: PyRandomString is a python library to generate N random list of string of M length. Ofcourse you can configure N and M
Home-page: https://github.com/ljnath/PyRandomString
Author: Lakhya Jyoti Nath (ljnath)
Author-email: ljnath@ljnath.com
License: MIT
Classifier: Development Status :: 5 - Production/Stable
Classifier: Intended Audience :: Developers
Classifier: Programming Language :: Python :: 3
Classifier: License :: OSI Approved :: MIT License
Classifier: Operating System :: OS Independent
Classifier: Topic :: Software Development :: Libraries
Classifier: Topic :: Utilities
Requires-Python: >=3.0
License-File: LICENSE
